{
  "annotations": {
    "changelogDate": "20260513073108"
  },
  "applications": ["protaskinxxw"],
  "dto": "mapstruct",
  "fields": [
    {
      "fieldName": "title",
      "fieldType": "String",
      "fieldValidateRules": ["required"]
    },
    {
      "fieldName": "message",
      "fieldType": "TextBlob"
    },
    {
      "fieldName": "sentAt",
      "fieldType": "Instant"
    },
    {
      "fieldName": "type",
      "fieldType": "Type",
      "fieldValues": "INFO,WARNING,ERROR"
    }
  ],
  "name": "Notification",
  "pagination": "pagination",
  "relationships": [
    {
      "otherEntityName": "appUser",
      "relationshipName": "user",
      "relationshipSide": "left",
      "relationshipType": "many-to-one"
    }
  ],
  "searchEngine": "no",
  "service": "serviceImpl"
}
